voice_forge/__init__.py
voice_forge/__main__.py
voice_forge/cli.py
voice_forge/main.py
voice_forge-1.0.0.dist-info/licenses/LICENSE
voice_forge-1.0.0.dist-info/METADATA
voice_forge-1.0.0.dist-info/WHEEL
voice_forge-1.0.0.dist-info/entry_points.txt
voice_forge-1.0.0.dist-info/top_level.txt
voice_forge-1.0.0.dist-info/RECORD
