Metadata-Version: 2.4
Name: voice-forge
Version: 1.0.0
Summary: A command-line tool for text-to-speech generation using Chatterbox TTS
Home-page: https://h3manth.com
Author: Hemanth HM
Author-email: Hemanth HM <hemanth.hm@gmail.com>
Maintainer-email: Hemanth HM <hemanth.hm@gmail.com>
License: MIT
Project-URL: Homepage, https://h3manth.com
Project-URL: Repository, https://github.com/hemanth/voice-forge
Project-URL: Bug Reports, https://github.com/hemanth/voice-forge/issues
Project-URL: Source, https://github.com/hemanth/voice-forge
Project-URL: Documentation, https://github.com/hemanth/voice-forge#readme
Keywords: tts,text-to-speech,voice,speech,chatterbox,cli
Classifier: Development Status :: 4 - Beta
Classifier: Intended Audience :: Developers
Classifier: Intended Audience :: End Users/Desktop
Classifier: License :: OSI Approved :: MIT License
Classifier: Operating System :: OS Independent
Classifier: Programming Language :: Python :: 3
Classifier: Programming Language :: Python :: 3.8
Classifier: Programming Language :: Python :: 3.9
Classifier: Programming Language :: Python :: 3.10
Classifier: Programming Language :: Python :: 3.11
Classifier: Programming Language :: Python :: 3.12
Classifier: Topic :: Multimedia :: Sound/Audio :: Speech
Classifier: Topic :: Software Development :: Libraries :: Python Modules
Classifier: Topic :: System :: System Shells
Classifier: Environment :: Console
Requires-Python: >=3.8
License-File: LICENSE
Requires-Dist: chatterbox-tts
Requires-Dist: torch>=1.9.0
Requires-Dist: torchaudio>=0.9.0
Requires-Dist: pygame>=2.0.0
Requires-Dist: playsound>=1.2.2
Provides-Extra: dev
Requires-Dist: pytest>=6.0; extra == "dev"
Requires-Dist: pytest-cov; extra == "dev"
Requires-Dist: black; extra == "dev"
Requires-Dist: flake8; extra == "dev"
Requires-Dist: mypy; extra == "dev"
Requires-Dist: build; extra == "dev"
Requires-Dist: twine; extra == "dev"
Dynamic: author
Dynamic: home-page
Dynamic: license-file
Dynamic: requires-python
